foliant/contrib/__init__.py
foliant/contrib/chapters.py
foliant/contrib/combined_options.py
foliant/contrib/header_anchors.py
foliant/contrib/utils.py
foliant/preprocessors/utils/__init__.py
foliant/preprocessors/utils/preprocessor_ext.py
foliantcontrib_utils-1.0.6.dist-info/licenses/LICENSE
foliantcontrib_utils-1.0.6.dist-info/METADATA
foliantcontrib_utils-1.0.6.dist-info/WHEEL
foliantcontrib_utils-1.0.6.dist-info/top_level.txt
foliantcontrib_utils-1.0.6.dist-info/RECORD
